{"grid_col":33,"grid_row":20,"vehicle_count":73,"window_start":"2026-04-02T07:28:45.000+02:00","window_end":"2026-04-02T07:28:55.000+02:00"}
{"grid_col":32,"grid_row":20,"vehicle_count":57,"window_start":"2026-04-02T07:28:45.000+02:00","window_end":"2026-04-02T07:28:55.000+02:00"}
{"grid_col":34,"grid_row":19,"vehicle_count":46,"window_start":"2026-04-02T07:28:45.000+02:00","window_end":"2026-04-02T07:28:55.000+02:00"}
{"grid_col":33,"grid_row":14,"vehicle_count":36,"window_start":"2026-04-02T07:28:45.000+02:00","window_end":"2026-04-02T07:28:55.000+02:00"}
{"grid_col":33,"grid_row":11,"vehicle_count":75,"window_start":"2026-04-02T07:28:45.000+02:00","window_end":"2026-04-02T07:28:55.000+02:00"}
