{"grid_col":17,"grid_row":16,"vehicle_count":36,"window_start":"2026-04-02T07:25:50.000+02:00","window_end":"2026-04-02T07:26:00.000+02:00"}
{"grid_col":18,"grid_row":19,"vehicle_count":58,"window_start":"2026-04-02T07:25:50.000+02:00","window_end":"2026-04-02T07:26:00.000+02:00"}
{"grid_col":21,"grid_row":9,"vehicle_count":36,"window_start":"2026-04-02T07:25:50.000+02:00","window_end":"2026-04-02T07:26:00.000+02:00"}
{"grid_col":28,"grid_row":9,"vehicle_count":25,"window_start":"2026-04-02T07:25:50.000+02:00","window_end":"2026-04-02T07:26:00.000+02:00"}
{"grid_col":23,"grid_row":9,"vehicle_count":64,"window_start":"2026-04-02T07:25:50.000+02:00","window_end":"2026-04-02T07:26:00.000+02:00"}
